test_ylang-0.11.1.dist-info/licenses/LICENSE
tests/__init__.py
tests/test_base.py
tests/test_quantization.py
tests/test_tpu_info.py
tests/test_utils.py
tests/tpu_backend_test.py
tests/core/__init__.py
tests/core/test_adapters.py
tests/core/test_core_tpu.py
tests/core/test_disagg_executor.py
tests/core/test_disagg_utils.py
tests/core/test_init.py
tests/kernels/__init__.py
tests/kernels/flash_attention_kernel_test.py
tests/kernels/quantized_matmul_kernel_test.py
tests/kernels/ragged_kv_cache_update_v2_test.py
tests/kernels/ragged_paged_attention_kernel_v2_test.py
tests/kernels/ragged_paged_attention_kernel_v3_test.py
tpu_commons/__init__.py
tpu_commons/backend.py
tpu_commons/logger.py
tpu_commons/tpu_info.py
tpu_commons/utils.py
tpu_commons/attention/__init__.py
tpu_commons/attention/backends/__init__.py
tpu_commons/attention/backends/pallas_torchax.py
tpu_commons/core/__init__.py
tpu_commons/core/adapters.py
tpu_commons/core/core_tpu.py
tpu_commons/core/disagg_executor.py
tpu_commons/core/disagg_utils.py
tpu_commons/distributed/__init__.py
tpu_commons/distributed/tpu_connector.py
tpu_commons/kernels/__init__.py
tpu_commons/kernels/quantized_matmul/__init__.py
tpu_commons/kernels/quantized_matmul/kernel.py
tpu_commons/kernels/quantized_matmul/tuned_block_sizes.py
tpu_commons/kernels/quantized_matmul/util.py
tpu_commons/kernels/ragged_paged_attention/__init__.py
tpu_commons/platforms/__init__.py
tpu_commons/platforms/tpu_jax.py
tpu_commons/platforms/tpu_torchax.py
tpu_commons/runner/__init__.py
tpu_commons/runner/block_table_jax.py
tpu_commons/runner/compilation_manager.py
tpu_commons/runner/input_batch_jax.py
tpu_commons/runner/kv_cache.py
tpu_commons/runner/kv_cache_manager.py
tpu_commons/runner/multimodal_manager.py
tpu_commons/runner/persistent_batch_manager.py
tpu_commons/runner/speculative_decoding_manager.py
tpu_commons/runner/structured_decoding_manager.py
tpu_commons/runner/tpu_jax_runner.py
tpu_commons/runner/utils.py
tpu_commons/worker/__init__.py
tpu_commons/worker/_temporary_vllm_compat.py
test_ylang-0.11.1.dist-info/METADATA
test_ylang-0.11.1.dist-info/WHEEL
test_ylang-0.11.1.dist-info/top_level.txt
test_ylang-0.11.1.dist-info/RECORD
