Metadata-Version: 2.4
Name: test-ylang
Version: 0.11.1
Author: tpu_commons Contributors
Classifier: Development Status :: 3 - Alpha
Classifier: Intended Audience :: Developers
Classifier: Intended Audience :: Education
Classifier: Intended Audience :: Science/Research
Classifier: License :: OSI Approved :: Apache Software License
Classifier: Programming Language :: Python :: 3.10
Classifier: Programming Language :: Python :: 3.11
Classifier: Programming Language :: Python :: 3.12
Classifier: Topic :: Scientific/Engineering :: Artificial Intelligence
Requires-Python: >=3.10
License-File: LICENSE
Requires-Dist: tpu-info
Requires-Dist: yapf==0.43.0
Requires-Dist: pytest
Requires-Dist: pytest-mock
Requires-Dist: absl-py
Requires-Dist: numpy
Requires-Dist: google-cloud-storage
Requires-Dist: jax==0.7.1
Requires-Dist: jaxlib==0.7.1
Requires-Dist: libtpu==0.0.23
Requires-Dist: jaxtyping
Requires-Dist: flax==0.11.1
Requires-Dist: torchax==0.0.5
Requires-Dist: qwix
Requires-Dist: pathwaysutils
Dynamic: author
Dynamic: classifier
Dynamic: description
Dynamic: description-content-type
Dynamic: license-file
Dynamic: requires-dist
Dynamic: requires-python
